graphics_maker/__init__.py
graphics_maker/animation_data.py
graphics_maker/graphics_maker.py
graphics_maker/object.py
graphics_maker/utils.py
graphics_maker-0.2.1.dist-info/LICENSE.txt
graphics_maker-0.2.1.dist-info/METADATA
graphics_maker-0.2.1.dist-info/WHEEL
graphics_maker-0.2.1.dist-info/top_level.txt
graphics_maker-0.2.1.dist-info/RECORD
