Metadata-Version: 2.1
Name: graphics-maker
Version: 0.2.1
Summary: simple graphics animation video generator
Home-page: https://github.com/DavidOberholzer/graphics-maker
Author: David Oberholzer
Author-email: davidobework@gmail.com
Project-URL: Bug Tracker, https://github.com/DavidOberholzer/graphics-maker/-/issues
Project-URL: repository, https://github.com/DavidOberholzer/graphics-maker
Classifier: Programming Language :: Python :: 3
Classifier: License :: OSI Approved :: MIT License
Classifier: Operating System :: OS Independent
Requires-Python: >=3.8
License-File: LICENSE.txt
Requires-Dist: gizeh ==0.1.11
Requires-Dist: moviepy ==1.0.3
Requires-Dist: numpy ==1.24.4
